pygwy_txt_analysis/__init__.py
pygwy_txt_analysis/pygwy_txt_analysis.py
pygwy_txt_analysis-0.0.1.dist-info/METADATA
pygwy_txt_analysis-0.0.1.dist-info/WHEEL
pygwy_txt_analysis-0.0.1.dist-info/licenses/LICENSE
pygwy_txt_analysis-0.0.1.dist-info/RECORD
