Metadata-Version: 2.4
Name: pygwy_txt_analysis
Version: 0.0.1
Summary: A library to analize and plot AFM scans
Project-URL: Homepage, https://github.com/UP-Smart-Soft-Matter/pygwy-txt-analysis
Project-URL: Issues, https://github.com/UP-Smart-Soft-Matter/pygwy-txt-analysis/issues
Author-email: Mika Music <mika.music@uni-potsdam.de>
License-Expression: LGPL-2.1-only
License-File: LICENSE
Classifier: Operating System :: OS Independent
Classifier: Programming Language :: Python :: 3
Requires-Python: >=3.9
Requires-Dist: astropy
Requires-Dist: lmfit
Requires-Dist: matplotlib
Requires-Dist: numpy
Requires-Dist: scipy
